jsl_elasticsearch/__init__.py
jsl_elasticsearch/_fields.py
jsl_elasticsearch/_render.py
jsl_elasticsearch-0.1.dev0.dist-info/DESCRIPTION.rst
jsl_elasticsearch-0.1.dev0.dist-info/METADATA
jsl_elasticsearch-0.1.dev0.dist-info/RECORD
jsl_elasticsearch-0.1.dev0.dist-info/WHEEL
jsl_elasticsearch-0.1.dev0.dist-info/metadata.json
jsl_elasticsearch-0.1.dev0.dist-info/top_level.txt
jsl_elasticsearch-0.1.dev0.dist-info/zip-safe
