Metadata-Version: 2.0
Name: jsl-elasticsearch
Version: 0.1.dev0
Summary: Generate ElasticSearch templates from JSL
Home-page: https://github.com/ncoghlan/jsl_elasticsearch
Author: Nick Coghlan
Author-email: ncoghlan@gmail.com
License: MIT
Keywords: jsl,elasticsearch
Platform: UNKNOWN
Classifier: Development Status :: 3 - Alpha
Classifier: Intended Audience :: Developers
Classifier: Natural Language :: English
Classifier: License :: OSI Approved :: MIT License
Classifier: Operating System :: OS Independent
Classifier: Programming Language :: Python
Classifier: Programming Language :: Python :: 3
Classifier: Programming Language :: Python :: 3 :: Only
Classifier: Programming Language :: Python :: 3.4
Classifier: Programming Language :: Python :: 3.5
Classifier: Programming Language :: Python :: Implementation :: CPython
Requires-Dist: jsl (>=0.2)
